{"latest":[{"id":329281,"title":"[에듀윌] 2022년 최신! 컴퓨터활용능력 1급 실기 단기패스","url":"https://www.inflearn.com/course/에듀윌-컴퓨터활용능력-1급-실기-단기패스","image":"","instructor":"에듀윌학습도우미"},{"id":329280,"title":"[에듀윌] 2022년 최신! 컴퓨터활용능력 1급 필기 단기패스","url":"https://www.inflearn.com/course/에듀윌-컴퓨터활용능력-1급-필기-단기패스","image":"","instructor":"에듀윌학습도우미"},{"id":329279,"title":"[에듀윌] 2022년 최신! 컴퓨터활용능력2급 실기 단기패스","url":"https://www.inflearn.com/course/에듀윌-컴퓨터활용능력-2급-실기-단기패스","image":"","instructor":"에듀윌학습도우미"},{"id":329253,"title":"데이터 기반 디지털트랜스포메이션 - DT 전략 마스터 클래스","url":"https://www.inflearn.com/course/디지털-트랜스포메이션-전략-마스터","image":"","instructor":"마소캠퍼스"},{"id":329250,"title":"[에듀윌] 2022년 최신! 컴퓨터활용능력2급 필기 단기패스","url":"https://www.inflearn.com/course/에듀윌-컴퓨터활용능력-2급-필기-단기패스","image":"","instructor":"에듀윌학습도우미"},{"id":329229,"title":"데이터 리터러시 Overview","url":"https://www.inflearn.com/course/데이터-리터러시-개요","image":"","instructor":"마소캠퍼스"},{"id":329057,"title":"[월간 데이터리안 웹 세미나 VOD] 2022년 7월 | 데이터 기반 의사 결정, 이렇게 합니다","url":"https://www.inflearn.com/course/월간-데이터리안-7월","image":"","instructor":"데이터리안"},{"id":329314,"title":"NFT 만들며 배우는 블록체인과 웹3 기초","url":"https://www.inflearn.com/course/nft-블록체인-웹3-기초","image":"","instructor":"박형주"},{"id":329319,"title":"파이썬 시작하기, Colab으로 배우는 핵심 강의 1","url":"https://www.inflearn.com/course/파이썬-시작-코랩","image":"","instructor":"노마드크리에이터"},{"id":329278,"title":"한 조각씩 배우는 SwiftUI - 입문편","url":"https://www.inflearn.com/course/한조각-swiftui-입문","image":"","instructor":"리이오"},{"id":329268,"title":"UI와 함께 배우는 Swift - 기초편","url":"https://www.inflearn.com/course/ui-swift-기초","image":"","instructor":"리이오"},{"id":329240,"title":"구글 캘린더 90초 꿀팁","url":"https://www.inflearn.com/course/구글-캘린더-90초-꿀팁","image":"","instructor":"마소캠퍼스"},{"id":329238,"title":"엑셀VBA 실전 프로그래밍","url":"https://www.inflearn.com/course/엑셀-vba-실전-프로그래밍","image":"","instructor":"엑셀장인"},{"id":329155,"title":"오피스 마녀의 엑셀 레시피 3편 - 피벗 테이블","url":"https://www.inflearn.com/course/오피스-마녀-엑셀-레시피-3","image":"","instructor":"Wisdomfactory"},{"id":329130,"title":"30분 요약강좌 시즌5 : 알잘딱깔센 flex &amp; grid","url":"https://www.inflearn.com/course/30분-시즌5-flex-gird","image":"","instructor":"제주코딩베이스캠프"},{"id":329018,"title":"초보 기획자/PM을 위한 Test Case 작성 및 QA 노하우","url":"https://www.inflearn.com/course/초보-pm-test-case-qa-노하우","image":"","instructor":"플래터"},{"id":327227,"title":"비트코인 암호화폐 자동매매 코인봇 만들기 Part 1","url":"https://www.inflearn.com/course/비트코인-암호화폐-자동매매-1","image":"","instructor":"AISchool"},{"id":329288,"title":"취삶선택 - 진짜 사명 찾기 가이드북","url":"https://www.inflearn.com/course/취삶선택-사명-찾기-가이드북","image":"","instructor":"라이프레이서"},{"id":329197,"title":"해외 명문대학 무료 온라인수업 무크(MOOC) 소화 방법","url":"https://www.inflearn.com/course/해외-무크-mooc","image":"","instructor":"김형률"},{"id":329251,"title":"솔리디티 깨부수기 - ERC20 (+ truffle, 프론트엔드)","url":"https://www.inflearn.com/course/솔리디티-깨부수기-2","image":"","instructor":"D_One"},{"id":328933,"title":"파이썬을 활용한 머신러닝 딥러닝 입문","url":"https://www.inflearn.com/course/파이썬-머신러닝-딥러닝-입문","image":"","instructor":"YoungJea Oh"},{"id":328478,"title":"Google Apps Script Uncharted - 구글 스프레드 시트 사무자동화 배우기","url":"https://www.inflearn.com/course/구글-스프레드-시트-사무-자동화","image":"","instructor":"Hansuk Kim"},{"id":329216,"title":"비트코인 선물 알고리즘 트레이딩","url":"https://www.inflearn.com/course/비트코인-선물-알고리즘-트레이딩","image":"","instructor":"멀티코어"},{"id":329052,"title":"앨런 iOS 아이폰 앱 개발 (15개의 앱을 만들면서 근본원리부터 배우는 UIKit)","url":"https://www.inflearn.com/course/ios-uikit-15apps","image":"","instructor":"앨런(Allen)"}],"popular":[{"id":325969,"title":"스프링 핵심 원리 - 기본편","url":"https://www.inflearn.com/course/스프링-핵심-원리-기본편","image":"","instructor":"김영한"},{"id":326277,"title":"모든 개발자를 위한 HTTP 웹 기본 지식","url":"https://www.inflearn.com/course/http-웹-네트워크","image":"","instructor":"김영한"},{"id":326674,"title":"스프링 MVC 1편  - 백엔드 웹 개발 핵심 기술","url":"https://www.inflearn.com/course/스프링-mvc-1","image":"","instructor":"김영한"},{"id":324109,"title":"자바 ORM 표준 JPA 프로그래밍 - 기본편","url":"https://www.inflearn.com/course/ORM-JPA-Basic","image":"","instructor":"김영한"},{"id":327260,"title":"스프링 MVC 2편 - 백엔드 웹 개발 활용 기술","url":"https://www.inflearn.com/course/스프링-mvc-2","image":"","instructor":"김영한"},{"id":327901,"title":"스프링 핵심 원리 - 고급편","url":"https://www.inflearn.com/course/스프링-핵심-원리-고급편","image":"","instructor":"김영한"},{"id":328990,"title":"스프링 DB 2편 - 데이터 접근 활용 기술","url":"https://www.inflearn.com/course/스프링-db-2","image":"","instructor":"김영한"},{"id":324119,"title":"실전! 스프링 부트와 JPA 활용1 - 웹 애플리케이션 개발","url":"https://www.inflearn.com/course/스프링부트-JPA-활용-1","image":"","instructor":"김영한"},{"id":328723,"title":"스프링 DB 1편 - 데이터 접근 핵심 원리","url":"https://www.inflearn.com/course/스프링-db-1","image":"","instructor":"김영한"},{"id":324214,"title":"실전! 스프링 부트와 JPA 활용2 - API 개발과 성능 최적화","url":"https://www.inflearn.com/course/스프링부트-JPA-API개발-성능최적화","image":"","instructor":"김영한"},{"id":326750,"title":"자바(Java) 알고리즘 문제풀이 : 코딩테스트 대비","url":"https://www.inflearn.com/course/자바-알고리즘-문제풀이-코테대비","image":"","instructor":"김태원"},{"id":326083,"title":"실전 자바스크립트","url":"https://www.inflearn.com/course/실전-자바스크립트","image":"","instructor":"이재승"},{"id":324474,"title":"실전! 스프링 데이터 JPA","url":"https://www.inflearn.com/course/스프링-데이터-JPA-실전","image":"","instructor":"김영한"},{"id":324476,"title":"실전! Querydsl","url":"https://www.inflearn.com/course/Querydsl-실전","image":"","instructor":"김영한"},{"id":329170,"title":"따라하며 배우는 리액트 A-Z","url":"https://www.inflearn.com/course/따라하는-리액트","image":"","instructor":"John Ahn"},{"id":324145,"title":"프로그래밍 시작하기 : 파이썬 입문 (Inflearn Original)","url":"https://www.inflearn.com/course/프로그래밍-파이썬-입문-인프런-오리지널","image":"","instructor":"인프런"},{"id":328284,"title":"제대로 파는 Git &amp; GitHub - by 얄코","url":"https://www.inflearn.com/course/제대로-파는-깃","image":"","instructor":"얄팍한 코딩사전"},{"id":326544,"title":"Spring Cloud로 개발하는 마이크로서비스 애플리케이션(MSA)","url":"https://www.inflearn.com/course/스프링-클라우드-마이크로서비스","image":"","instructor":"Dowon Lee"},{"id":326485,"title":"10주완성 C++ 코딩테스트 | 알고리즘 IT취업","url":"https://www.inflearn.com/course/10주완성-코딩테스트-큰돌","image":"","instructor":"큰돌"},{"id":328520,"title":"[핵집] 빅데이터 분석기사(필기)_과목 1~2","url":"https://www.inflearn.com/course/핵집-빅분기-필기12","image":"","instructor":"소확성"},{"id":328527,"title":"[핵집] 빅데이터 분석기사(필기)_과목 3~4","url":"https://www.inflearn.com/course/핵집-빅분기-필기34","image":"","instructor":"소확성"},{"id":324482,"title":"홍정모의 따라하며 배우는 C언어","url":"https://www.inflearn.com/course/following-c","image":"","instructor":"PP TREE"},{"id":326174,"title":"비전공자를 위한 진짜 입문 올인원 개발 클래스","url":"https://www.inflearn.com/course/올인원-개발클래스","image":"","instructor":"그랩"},{"id":328329,"title":"[코드팩토리] [초급] Flutter 3.0 앱 개발 - 10개의 프로젝트로 오늘 초보 탈출!","url":"https://www.inflearn.com/course/플러터-프로젝트","image":"","instructor":"코드팩토리"}],"popularPaid":[{"id":325969,"title":"스프링 핵심 원리 - 기본편","url":"https://www.inflearn.com/course/스프링-핵심-원리-기본편","image":"","instructor":"김영한"},{"id":326277,"title":"모든 개발자를 위한 HTTP 웹 기본 지식","url":"https://www.inflearn.com/course/http-웹-네트워크","image":"","instructor":"김영한"},{"id":326674,"title":"스프링 MVC 1편  - 백엔드 웹 개발 핵심 기술","url":"https://www.inflearn.com/course/스프링-mvc-1","image":"","instructor":"김영한"},{"id":324109,"title":"자바 ORM 표준 JPA 프로그래밍 - 기본편","url":"https://www.inflearn.com/course/ORM-JPA-Basic","image":"","instructor":"김영한"},{"id":327260,"title":"스프링 MVC 2편 - 백엔드 웹 개발 활용 기술","url":"https://www.inflearn.com/course/스프링-mvc-2","image":"","instructor":"김영한"},{"id":327901,"title":"스프링 핵심 원리 - 고급편","url":"https://www.inflearn.com/course/스프링-핵심-원리-고급편","image":"","instructor":"김영한"},{"id":328990,"title":"스프링 DB 2편 - 데이터 접근 활용 기술","url":"https://www.inflearn.com/course/스프링-db-2","image":"","instructor":"김영한"},{"id":324119,"title":"실전! 스프링 부트와 JPA 활용1 - 웹 애플리케이션 개발","url":"https://www.inflearn.com/course/스프링부트-JPA-활용-1","image":"","instructor":"김영한"},{"id":328723,"title":"스프링 DB 1편 - 데이터 접근 핵심 원리","url":"https://www.inflearn.com/course/스프링-db-1","image":"","instructor":"김영한"},{"id":324214,"title":"실전! 스프링 부트와 JPA 활용2 - API 개발과 성능 최적화","url":"https://www.inflearn.com/course/스프링부트-JPA-API개발-성능최적화","image":"","instructor":"김영한"},{"id":326750,"title":"자바(Java) 알고리즘 문제풀이 : 코딩테스트 대비","url":"https://www.inflearn.com/course/자바-알고리즘-문제풀이-코테대비","image":"","instructor":"김태원"},{"id":326083,"title":"실전 자바스크립트","url":"https://www.inflearn.com/course/실전-자바스크립트","image":"","instructor":"이재승"},{"id":324474,"title":"실전! 스프링 데이터 JPA","url":"https://www.inflearn.com/course/스프링-데이터-JPA-실전","image":"","instructor":"김영한"},{"id":324476,"title":"실전! Querydsl","url":"https://www.inflearn.com/course/Querydsl-실전","image":"","instructor":"김영한"},{"id":329170,"title":"따라하며 배우는 리액트 A-Z","url":"https://www.inflearn.com/course/따라하는-리액트","image":"","instructor":"John Ahn"},{"id":324145,"title":"프로그래밍 시작하기 : 파이썬 입문 (Inflearn Original)","url":"https://www.inflearn.com/course/프로그래밍-파이썬-입문-인프런-오리지널","image":"","instructor":"인프런"},{"id":328284,"title":"제대로 파는 Git &amp; GitHub - by 얄코","url":"https://www.inflearn.com/course/제대로-파는-깃","image":"","instructor":"얄팍한 코딩사전"},{"id":326544,"title":"Spring Cloud로 개발하는 마이크로서비스 애플리케이션(MSA)","url":"https://www.inflearn.com/course/스프링-클라우드-마이크로서비스","image":"","instructor":"Dowon Lee"},{"id":326485,"title":"10주완성 C++ 코딩테스트 | 알고리즘 IT취업","url":"https://www.inflearn.com/course/10주완성-코딩테스트-큰돌","image":"","instructor":"큰돌"},{"id":328520,"title":"[핵집] 빅데이터 분석기사(필기)_과목 1~2","url":"https://www.inflearn.com/course/핵집-빅분기-필기12","image":"","instructor":"소확성"},{"id":328527,"title":"[핵집] 빅데이터 분석기사(필기)_과목 3~4","url":"https://www.inflearn.com/course/핵집-빅분기-필기34","image":"","instructor":"소확성"},{"id":324482,"title":"홍정모의 따라하며 배우는 C언어","url":"https://www.inflearn.com/course/following-c","image":"","instructor":"PP TREE"},{"id":326174,"title":"비전공자를 위한 진짜 입문 올인원 개발 클래스","url":"https://www.inflearn.com/course/올인원-개발클래스","image":"","instructor":"그랩"},{"id":328329,"title":"[코드팩토리] [초급] Flutter 3.0 앱 개발 - 10개의 프로젝트로 오늘 초보 탈출!","url":"https://www.inflearn.com/course/플러터-프로젝트","image":"","instructor":"코드팩토리"}],"popularFree":[{"id":325630,"title":"스프링 입문 - 코드로 배우는 스프링 부트, 웹 MVC, DB 접근 기술","url":"https://www.inflearn.com/course/스프링-입문-스프링부트","image":"","instructor":"김영한"},{"id":21946,"title":"'이것이 리눅스다' 저자의 Red Hat CentOS7 리눅스 서버&네트워크 강좌","url":"https://www.inflearn.com/course/이것이-리눅스다","image":"","instructor":"한빛미디어"},{"id":292508,"title":"Do it! 자바 프로그래밍 입문","url":"https://www.inflearn.com/course/자바-프로그래밍-입문","image":"","instructor":"이지스퍼블리싱"},{"id":326392,"title":"Spring Boot JWT Tutorial","url":"https://www.inflearn.com/course/스프링부트-jwt","image":"","instructor":"정은구"},{"id":77623,"title":"[김왼손의 왼손코딩] 미운코딩새끼: 4시간 만에 끝내는 파이썬 기초 (전자책 포함)","url":"https://www.inflearn.com/course/파이썬-기초-강좌","image":"","instructor":"김왼손의 왼손코딩"},{"id":326346,"title":"운영체제 공룡책 강의","url":"https://www.inflearn.com/course/운영체제-공룡책-전공강의","image":"","instructor":"주니온"},{"id":324216,"title":"2022 30분 요약 강좌 시즌 1 : HTML, CSS, Linux, Bootstrap, Python, JS,  jQuery&amp;Ajax","url":"https://www.inflearn.com/course/제주코딩-웹개발-30분요약","image":"","instructor":"제주코딩베이스캠프"},{"id":326050,"title":"Tensorflow 사용메뉴얼","url":"https://www.inflearn.com/course/텐서플로-딥러닝-구현","image":"","instructor":"공대형아"},{"id":324951,"title":"따라하며 배우는 노드, 리액트 시리즈 - 기본 강의","url":"https://www.inflearn.com/course/따라하며-배우는-노드-리액트-기본","image":"","instructor":"John Ahn"},{"id":324063,"title":"웹 게임을 만들며 배우는 React","url":"https://www.inflearn.com/course/web-game-react","image":"","instructor":"조현영"},{"id":329130,"title":"30분 요약강좌 시즌5 : 알잘딱깔센 flex &amp; grid","url":"https://www.inflearn.com/course/30분-시즌5-flex-gird","image":"","instructor":"제주코딩베이스캠프"},{"id":326716,"title":"[백문이불여일타] 데이터 분석을 위한 SQL 실전편 (무료 미니 코스)","url":"https://www.inflearn.com/course/데이터-분석-sql-실전","image":"","instructor":"데이터리안"},{"id":327798,"title":"비 개발자들을 위한 IT 개발 지식","url":"https://www.inflearn.com/course/비개발자-it-개발-지식","image":"","instructor":"불꽃남자25"},{"id":328464,"title":"자바스크립트 중급 강좌","url":"https://www.inflearn.com/course/자바스크립트-중급","image":"","instructor":"코딩앙마"},{"id":38407,"title":"모두를 위한 딥러닝 - Deep Reinforcement Learning","url":"https://www.inflearn.com/course/reinforcement-learning","image":"","instructor":"Sung Kim"},{"id":324152,"title":"누구나 할 수 있다! 이모티콘 만들기","url":"https://www.inflearn.com/course/디자인-이모티콘-소콘소콘","image":"","instructor":"소콘소콘"},{"id":325341,"title":"생애 첫 SQL With 제코베","url":"https://www.inflearn.com/course/sql-기초-제주코딩베이스캠프","image":"","instructor":"제주코딩베이스캠프"},{"id":221292,"title":"스프링 프레임워크 입문","url":"https://www.inflearn.com/course/spring","image":"","instructor":"백기선"},{"id":37069,"title":"ELK 스택 (ElasticSearch, Logstash, Kibana) 으로 데이터 분석","url":"https://www.inflearn.com/course/elk-스택-데이터-분석","image":"","instructor":"Minsuk Heo"},{"id":326749,"title":"제품 관리자와 서비스 기획자를 위한 실전 노하우 - 아낌없이 드립니다!","url":"https://www.inflearn.com/course/제품-관리자-실전-노하우","image":"","instructor":"기획자 데이먼"},{"id":328073,"title":"스프링부트 시큐리티 &amp; JWT 강의","url":"https://www.inflearn.com/course/스프링부트-시큐리티","image":"","instructor":"최주호"},{"id":327067,"title":"컴알못이 보는 컴퓨터 하드웨어 기초상식","url":"https://www.inflearn.com/course/컴퓨터-하드웨어-기초상식","image":"","instructor":"제주코딩베이스캠프"},{"id":329167,"title":"게임처럼 공부하는 git 던전","url":"https://www.inflearn.com/course/게임처럼-git던전","image":"","instructor":"리이오"},{"id":20117,"title":"웹브라우저 Javascript (자바스크립트)","url":"https://www.inflearn.com/course/javascript-자바스크립트-강좌","image":"","instructor":"Egoing Lee"}]}