{"latest":[{"id":328823,"title":"개발자면접을 위한 CS전공지식 [CS면접]","url":"https://www.inflearn.com/course/개발자-면접-cs-특강","image":"","instructor":"큰돌"},{"id":328784,"title":"안전한 홈 네트워크를 위한 보안강화: 홈 네트워크 보안을 위한 첫 걸음","url":"https://www.inflearn.com/course/홈네트워크-보안-첫걸음","image":"","instructor":"한국정보보호교육센터"},{"id":328778,"title":"WPF (C#, 자막제공)","url":"https://www.inflearn.com/course/wpf-subtitles","image":"","instructor":"개발자 Park"},{"id":328605,"title":"ASP.NET core Blazor 프레임워크 맛보기","url":"https://www.inflearn.com/course/asp-dot-net-core-blazor","image":"","instructor":"백승철"},{"id":328853,"title":"SQL 개발자 (SQLD) 자격증 따기 Part.3","url":"https://www.inflearn.com/course/sqld-자격증-초급-3","image":"","instructor":"유용한IT학습"},{"id":328817,"title":"C++로 만드는 언리얼엔진 게임포트폴리오 시리즈 Stage4","url":"https://www.inflearn.com/course/언리얼-엔진-게임포폴4","image":"","instructor":"코사트"},{"id":328742,"title":"네트워크, 그림으로 이해하자","url":"https://www.inflearn.com/course/네트워크-그림-이해","image":"","instructor":"예술하는 개발자"},{"id":328725,"title":"무조건 따라하면 카카오뷰 초보도 하루만에 대박 노출 올리는 비법","url":"https://www.inflearn.com/course/따라하며-배우는-카카오뷰-초보","image":"","instructor":"윈플즈"},{"id":328721,"title":"비전공자를 위한 풀스택 맛집지도 만들기 프로젝트!: Front, Back-end 그리고 배포까지","url":"https://www.inflearn.com/course/비전공-풀스택-맛집지도","image":"","instructor":"Jiwoon Jeong"},{"id":328711,"title":"비즈니스 애널리틱스, 비즈니스 현황분석 실무 마스터 클래스","url":"https://www.inflearn.com/course/비즈니스-애널리틱스-현황분석","image":"","instructor":"마소캠퍼스"},{"id":328743,"title":"[개념은 호옹~, 실습 빡] SQL 데이터 분석, 활용!","url":"https://www.inflearn.com/course/개념실습-데이터분석-활용","image":"","instructor":"홍팍"},{"id":328741,"title":"[개념은 호옹~, 실습 빡] SQL 데이터 분석, 입문!","url":"https://www.inflearn.com/course/개념실습-데이터분석-입문","image":"","instructor":"홍팍"},{"id":328740,"title":"공공데이터를 이용해 SQL을 배워보자","url":"https://www.inflearn.com/course/공공데이터-sql-학습","image":"","instructor":"소프트웨어알림장"},{"id":328720,"title":"파이널컷프로 X 기초 때려잡기 PERPECT 강좌","url":"https://www.inflearn.com/course/파이널컷프로-때려잡기-에듀픽","image":"","instructor":"EDUPIC 미디어 강좌."},{"id":327740,"title":"마이크로넛 자바 클라우드 어플리케이션 제작","url":"https://www.inflearn.com/course/마이크로넛-클라우드-네이티브","image":"","instructor":"Billy Lee"},{"id":328739,"title":"CSS 레이아웃 - flex &amp; grid","url":"https://www.inflearn.com/course/css-레이아웃-flex-grid","image":"","instructor":"유노코딩"},{"id":328756,"title":"[최신 React 버전 반영] 초보자도 쉽게 만드는 React 웹 서비스 만들기","url":"https://www.inflearn.com/course/초보자도-react-웹서비스","image":"","instructor":"에피노"},{"id":328754,"title":"2022 ISMS-P 인증심사원 자격검정 Add-on 인증기준 결함 문제풀이","url":"https://www.inflearn.com/course/isms-p-2022-문제풀이","image":"","instructor":"보안프로젝트"},{"id":328704,"title":"이더리움 디앱(dApp) 개발과 프로젝트, 블록체인 스마트 컨트랙트","url":"https://www.inflearn.com/course/이더리움-디앱개발-블록체인","image":"","instructor":"보안프로젝트"},{"id":328609,"title":"jQuery로 구현하는 NFT 마켓플레이스 (이더리움, 폴리곤)","url":"https://www.inflearn.com/course/제이쿼리-nft-마켓플레이스","image":"","instructor":"Kyung-il In"},{"id":328552,"title":"지식을 흡수하는 독서법을 알려드립니다","url":"https://www.inflearn.com/course/지식을-흡수하는-독서법","image":"","instructor":"라이프레이서"},{"id":328547,"title":"C4D와 Octane render","url":"https://www.inflearn.com/course/c4d-octane-render","image":"","instructor":"판다주임"},{"id":327155,"title":"실습으로 배우는 AWS(Amazon Web Services) 클라우드 컴퓨팅 입문","url":"https://www.inflearn.com/course/실습-클라우드-컴퓨팅-입문","image":"","instructor":"AISchool"},{"id":328460,"title":"두고두고 써먹는 유니티 VR","url":"https://www.inflearn.com/course/두고두고-유니티-vr","image":"","instructor":"오민석"}],"popular":[{"id":327795,"title":"스마트폰으로 프리미어 프로급 영상 제작하기","url":"https://www.inflearn.com/course/스마트폰-영상-제작","image":"","instructor":"소확성"},{"id":325457,"title":"[직딩꿀템] 디자이너 없이 뚝딱 만드는 디자인 콘텐츠 feat. 망고보드","url":"https://www.inflearn.com/course/직딩꿀템-망고보드-디자인콘텐츠","image":"","instructor":"멀티캠퍼스"},{"id":325969,"title":"스프링 핵심 원리 - 기본편","url":"https://www.inflearn.com/course/스프링-핵심-원리-기본편","image":"","instructor":"김영한"},{"id":325446,"title":"[직딩꿀템] 직장인 글쓰기 트레이닝, 일하는 문장들","url":"https://www.inflearn.com/course/직딩꿀템-직장인-글쓰기","image":"","instructor":"멀티캠퍼스"},{"id":324314,"title":"업무가 100배 빨라지는 엑셀 데이터 활용과 분석 노하우","url":"https://www.inflearn.com/course/엑셀-데이터-활용-분석","image":"","instructor":"김경자"},{"id":327901,"title":"스프링 핵심 원리 - 고급편","url":"https://www.inflearn.com/course/스프링-핵심-원리-고급편","image":"","instructor":"김영한"},{"id":328723,"title":"스프링 DB 1편 - 데이터 접근 핵심 원리","url":"https://www.inflearn.com/course/스프링-db-1","image":"","instructor":"김영한"},{"id":326277,"title":"모든 개발자를 위한 HTTP 웹 기본 지식","url":"https://www.inflearn.com/course/http-웹-네트워크","image":"","instructor":"김영한"},{"id":325900,"title":"Outlook과 OneNote로 스마트한 업무 시스템 만들기","url":"https://www.inflearn.com/course/스마트워크-아웃룩-원노트","image":"","instructor":"오피스튜터"},{"id":326674,"title":"스프링 MVC 1편  - 백엔드 웹 개발 핵심 기술","url":"https://www.inflearn.com/course/스프링-mvc-1","image":"","instructor":"김영한"},{"id":327260,"title":"스프링 MVC 2편 - 백엔드 웹 개발 활용 기술","url":"https://www.inflearn.com/course/스프링-mvc-2","image":"","instructor":"김영한"},{"id":325082,"title":"엑셀 매크로와 VBA 기초부터 실무활용까지 완전 정복","url":"https://www.inflearn.com/course/엑셀-매크로-vba-기초-실무활용","image":"","instructor":"김경자"},{"id":327960,"title":"데이터 리터러시 - 데이터 읽고 쓰기의 기술","url":"https://www.inflearn.com/course/데이터-리터러시-읽고쓰기","image":"","instructor":"마소캠퍼스"},{"id":324109,"title":"자바 ORM 표준 JPA 프로그래밍 - 기본편","url":"https://www.inflearn.com/course/ORM-JPA-Basic","image":"","instructor":"김영한"},{"id":324119,"title":"실전! 스프링 부트와 JPA 활용1 - 웹 애플리케이션 개발","url":"https://www.inflearn.com/course/스프링부트-JPA-활용-1","image":"","instructor":"김영한"},{"id":135995,"title":"프로들만의 차별화된 엑셀 데이터 분석과 차트 시각화","url":"https://www.inflearn.com/course/excel-엑셀-데이터-분석","image":"","instructor":"김경자"},{"id":326741,"title":"업무 자동화하기 Level 2 - Power Automate","url":"https://www.inflearn.com/course/업무-자동화-2","image":"","instructor":"오마스"},{"id":324214,"title":"실전! 스프링 부트와 JPA 활용2 - API 개발과 성능 최적화","url":"https://www.inflearn.com/course/스프링부트-JPA-API개발-성능최적화","image":"","instructor":"김영한"},{"id":324476,"title":"실전! Querydsl","url":"https://www.inflearn.com/course/Querydsl-실전","image":"","instructor":"김영한"},{"id":324088,"title":"Vue.js 시작하기 - Age of Vue.js","url":"https://www.inflearn.com/course/age-of-vuejs","image":"","instructor":"장기효(캡틴판교)"},{"id":324474,"title":"실전! 스프링 데이터 JPA","url":"https://www.inflearn.com/course/스프링-데이터-JPA-실전","image":"","instructor":"김영한"},{"id":326544,"title":"Spring Cloud로 개발하는 마이크로서비스 애플리케이션(MSA)","url":"https://www.inflearn.com/course/스프링-클라우드-마이크로서비스","image":"","instructor":"Dowon Lee"},{"id":326197,"title":"VR, AR 기초 이론과 시장 분석","url":"https://www.inflearn.com/course/vr-ar-기초이론","image":"","instructor":"유용한IT학습"},{"id":326770,"title":"쉽고 빠르게 익히는 Power BI 심화 1 (시각화와 파워 쿼리)","url":"https://www.inflearn.com/course/power-bi-심화1","image":"","instructor":"오피스튜터"}],"popularPaid":[{"id":327795,"title":"스마트폰으로 프리미어 프로급 영상 제작하기","url":"https://www.inflearn.com/course/스마트폰-영상-제작","image":"","instructor":"소확성"},{"id":325457,"title":"[직딩꿀템] 디자이너 없이 뚝딱 만드는 디자인 콘텐츠 feat. 망고보드","url":"https://www.inflearn.com/course/직딩꿀템-망고보드-디자인콘텐츠","image":"","instructor":"멀티캠퍼스"},{"id":325969,"title":"스프링 핵심 원리 - 기본편","url":"https://www.inflearn.com/course/스프링-핵심-원리-기본편","image":"","instructor":"김영한"},{"id":325446,"title":"[직딩꿀템] 직장인 글쓰기 트레이닝, 일하는 문장들","url":"https://www.inflearn.com/course/직딩꿀템-직장인-글쓰기","image":"","instructor":"멀티캠퍼스"},{"id":324314,"title":"업무가 100배 빨라지는 엑셀 데이터 활용과 분석 노하우","url":"https://www.inflearn.com/course/엑셀-데이터-활용-분석","image":"","instructor":"김경자"},{"id":327901,"title":"스프링 핵심 원리 - 고급편","url":"https://www.inflearn.com/course/스프링-핵심-원리-고급편","image":"","instructor":"김영한"},{"id":328723,"title":"스프링 DB 1편 - 데이터 접근 핵심 원리","url":"https://www.inflearn.com/course/스프링-db-1","image":"","instructor":"김영한"},{"id":326277,"title":"모든 개발자를 위한 HTTP 웹 기본 지식","url":"https://www.inflearn.com/course/http-웹-네트워크","image":"","instructor":"김영한"},{"id":325900,"title":"Outlook과 OneNote로 스마트한 업무 시스템 만들기","url":"https://www.inflearn.com/course/스마트워크-아웃룩-원노트","image":"","instructor":"오피스튜터"},{"id":326674,"title":"스프링 MVC 1편  - 백엔드 웹 개발 핵심 기술","url":"https://www.inflearn.com/course/스프링-mvc-1","image":"","instructor":"김영한"},{"id":327260,"title":"스프링 MVC 2편 - 백엔드 웹 개발 활용 기술","url":"https://www.inflearn.com/course/스프링-mvc-2","image":"","instructor":"김영한"},{"id":325082,"title":"엑셀 매크로와 VBA 기초부터 실무활용까지 완전 정복","url":"https://www.inflearn.com/course/엑셀-매크로-vba-기초-실무활용","image":"","instructor":"김경자"},{"id":327960,"title":"데이터 리터러시 - 데이터 읽고 쓰기의 기술","url":"https://www.inflearn.com/course/데이터-리터러시-읽고쓰기","image":"","instructor":"마소캠퍼스"},{"id":324109,"title":"자바 ORM 표준 JPA 프로그래밍 - 기본편","url":"https://www.inflearn.com/course/ORM-JPA-Basic","image":"","instructor":"김영한"},{"id":324119,"title":"실전! 스프링 부트와 JPA 활용1 - 웹 애플리케이션 개발","url":"https://www.inflearn.com/course/스프링부트-JPA-활용-1","image":"","instructor":"김영한"},{"id":135995,"title":"프로들만의 차별화된 엑셀 데이터 분석과 차트 시각화","url":"https://www.inflearn.com/course/excel-엑셀-데이터-분석","image":"","instructor":"김경자"},{"id":326741,"title":"업무 자동화하기 Level 2 - Power Automate","url":"https://www.inflearn.com/course/업무-자동화-2","image":"","instructor":"오마스"},{"id":324214,"title":"실전! 스프링 부트와 JPA 활용2 - API 개발과 성능 최적화","url":"https://www.inflearn.com/course/스프링부트-JPA-API개발-성능최적화","image":"","instructor":"김영한"},{"id":324476,"title":"실전! Querydsl","url":"https://www.inflearn.com/course/Querydsl-실전","image":"","instructor":"김영한"},{"id":324088,"title":"Vue.js 시작하기 - Age of Vue.js","url":"https://www.inflearn.com/course/age-of-vuejs","image":"","instructor":"장기효(캡틴판교)"},{"id":324474,"title":"실전! 스프링 데이터 JPA","url":"https://www.inflearn.com/course/스프링-데이터-JPA-실전","image":"","instructor":"김영한"},{"id":326544,"title":"Spring Cloud로 개발하는 마이크로서비스 애플리케이션(MSA)","url":"https://www.inflearn.com/course/스프링-클라우드-마이크로서비스","image":"","instructor":"Dowon Lee"},{"id":326197,"title":"VR, AR 기초 이론과 시장 분석","url":"https://www.inflearn.com/course/vr-ar-기초이론","image":"","instructor":"유용한IT학습"},{"id":326770,"title":"쉽고 빠르게 익히는 Power BI 심화 1 (시각화와 파워 쿼리)","url":"https://www.inflearn.com/course/power-bi-심화1","image":"","instructor":"오피스튜터"}],"popularFree":[{"id":325950,"title":"Do it! 키트 없이 배우는 아두이노","url":"https://www.inflearn.com/course/키트없이-배우는-아두이노","image":"","instructor":"메이커멘토"},{"id":328823,"title":"개발자면접을 위한 CS전공지식 [CS면접]","url":"https://www.inflearn.com/course/개발자-면접-cs-특강","image":"","instructor":"큰돌"},{"id":134573,"title":"화이트해커가 되기 위한 8가지 웹 해킹 기술","url":"https://www.inflearn.com/course/화이트해커가-되기위한-8가지","image":"","instructor":"시큐아카데미"},{"id":325630,"title":"스프링 입문 - 코드로 배우는 스프링 부트, 웹 MVC, DB 접근 기술","url":"https://www.inflearn.com/course/스프링-입문-스프링부트","image":"","instructor":"김영한"},{"id":194516,"title":"Git과 GitHub 시작하기","url":"https://www.inflearn.com/course/git-and-github","image":"","instructor":"호눅스"},{"id":326507,"title":"[데브원영] 아파치 카프카 for beginners","url":"https://www.inflearn.com/course/아파치-카프카-입문","image":"","instructor":"데브원영 DVWY"},{"id":327974,"title":"모던 자바스크립트 딥다이브 스터디","url":"https://www.inflearn.com/course/모던-자바스크립트-딥다이브","image":"","instructor":"정재남"},{"id":77623,"title":"[김왼손의 왼손코딩] 미운코딩새끼: 4시간 만에 끝내는 파이썬 기초 (전자책 포함)","url":"https://www.inflearn.com/course/파이썬-기초-강좌","image":"","instructor":"김왼손의 왼손코딩"},{"id":37069,"title":"ELK 스택 (ElasticSearch, Logstash, Kibana) 으로 데이터 분석","url":"https://www.inflearn.com/course/elk-스택-데이터-분석","image":"","instructor":"Minsuk Heo"},{"id":20275,"title":"생활코딩 - 정규표현식","url":"https://www.inflearn.com/course/생활코딩-정규표현식","image":"","instructor":"Egoing Lee"},{"id":327126,"title":"[리뉴얼] 렛츠기릿 자바스크립트","url":"https://www.inflearn.com/course/레츠기릿-자바스크립트","image":"","instructor":"조현영"},{"id":326205,"title":"자바 스프링부트 활용 웹개발 실무용","url":"https://www.inflearn.com/course/backend-송자바","image":"","instructor":"송자바코딩"},{"id":47893,"title":"자바스크립트로 알아보는 함수형 프로그래밍 (ES5)","url":"https://www.inflearn.com/course/함수형-프로그래밍","image":"","instructor":"유인동"},{"id":326295,"title":"Svelte.js 입문 가이드","url":"https://www.inflearn.com/course/스벨트-입문-가이드","image":"","instructor":"HEROPY"},{"id":328599,"title":"30분 요약 강좌 시즌4 : 알잘딱깔센 GitHub","url":"https://www.inflearn.com/course/30분-시즌4-깃허브","image":"","instructor":"제주코딩베이스캠프"},{"id":323992,"title":"예제로 배우는 스프링 입문 (개정판)","url":"https://www.inflearn.com/course/spring_revised_edition","image":"","instructor":"백기선"},{"id":328287,"title":"프론트엔드 면접 1시간전","url":"https://www.inflearn.com/course/프론트엔드-면접-큰돌","image":"","instructor":"큰돌"},{"id":155714,"title":"WEB2 - Node.js","url":"https://www.inflearn.com/course/web2-node-js","image":"","instructor":"Egoing Lee"},{"id":328372,"title":"[D.P.(DappProject)] 디앱 프로젝트(NFT 생성, NFT 구매 및 판매)","url":"https://www.inflearn.com/course/디앱-프로젝트","image":"","instructor":"h662"},{"id":324172,"title":"SwiftUI 개념 익히기","url":"https://www.inflearn.com/course/SwiftUI-개념-iOS","image":"","instructor":"Hohyeon Moon"},{"id":324061,"title":"[애플 공식 교재] 스위프트 퍼즐 1","url":"https://www.inflearn.com/course/swift-high-coding1","image":"","instructor":"코더스하이"},{"id":286212,"title":"정보보안 및 개인정보보호 특강","url":"https://www.inflearn.com/course/정보보안-및-개인정보보호","image":"","instructor":"장용하"},{"id":324947,"title":"SELECT ALL FROM SQL","url":"https://www.inflearn.com/course/sql-select","image":"","instructor":"박범진"},{"id":324186,"title":"데이터 시각화와 차트분석 기법","url":"https://www.inflearn.com/course/데이터-시각화-차트분석","image":"","instructor":"노마드크리에이터"}]}